<?xml version="1.0" encoding="UTF-8"?>
<navigationModel
  ns = "http://schemas.android.com?import=com.android.tools.idea.editors.navigation.model.*">
  <locations  
    class = "java.util.ArrayList">
    <statePointEntry>
      <state      
        class = "com.android.tools.idea.editors.navigation.model.ActivityState"      
        className = "android.validcat.net.helloworld.MainActivity"/>
      <point      
        x = "-124"      
        y = "136"/>
    </statePointEntry>
    <statePointEntry>
      <state      
        class = "com.android.tools.idea.editors.navigation.model.ActivityState"      
        className = "android.validcat.net.helloworld.MainActivity2"/>
      <point      
        x = "1104"      
        y = "600"/>
    </statePointEntry>
    <statePointEntry>
      <state      
        class = "com.android.tools.idea.editors.navigation.model.ActivityState"      
        className = "android.validcat.net.helloworld.MainActivity3"/>
      <point      
        x = "792"      
        y = "28"/>
    </statePointEntry>
  </locations>
</navigationModel>
